<?xml version="1.0" encoding="UTF-8"?>

<openerp>
    <data noupdate="0">

        <record model="ir.ui.menu" id="menu_developement_tools" >
            <field name="name">Development</field>
            <field name="sequence" eval="10" />
        </record>

        <record model="ir.ui.menu" id="menu_testing_tools" >
            <field name="name">Testing tools</field>
            <field name="parent_id" ref="menu_developement_tools" />
            <field name="sequence" eval="10" />
        </record>

    </data>
</openerp>
